mecha/__init__.py
mecha/__main__.py
mecha/api.py
mecha/ast.py
mecha/cli.py
mecha/commands.py
mecha/config.py
mecha/contrib/__init__.py
mecha/contrib/annotate_diagnostics.py
mecha/contrib/bake_macros.py
mecha/contrib/clear_diagnostics.py
mecha/contrib/debug_ast.py
mecha/contrib/embed.py
mecha/contrib/implicit_execute.py
mecha/contrib/inline_function_tag.py
mecha/contrib/json_files.py
mecha/contrib/lint_basic.py
mecha/contrib/messages.py
mecha/contrib/nested_location.py
mecha/contrib/nested_resources.py
mecha/contrib/nested_yaml.py
mecha/contrib/nesting.py
mecha/contrib/raw.py
mecha/contrib/relative_location.py
mecha/contrib/source_map.py
mecha/contrib/statistics.py
mecha/contrib/validation/__init__.py
mecha/contrib/validation/mcdoc.py
mecha/database.py
mecha/diagnostic.py
mecha/dispatch.py
mecha/error.py
mecha/parse.py
mecha/plugin.py
mecha/preprocess.py
mecha/prototype.py
mecha/py.typed
mecha/resources/1_14.json
mecha/resources/1_14_1.json
mecha/resources/1_14_2.json
mecha/resources/1_14_3.json
mecha/resources/1_14_4.json
mecha/resources/1_15.json
mecha/resources/1_15_1.json
mecha/resources/1_15_2.json
mecha/resources/1_16.json
mecha/resources/1_16_1.json
mecha/resources/1_16_2.json
mecha/resources/1_16_3.json
mecha/resources/1_16_4.json
mecha/resources/1_16_5.json
mecha/resources/1_17.json
mecha/resources/1_17_1.json
mecha/resources/1_18.json
mecha/resources/1_18_1.json
mecha/resources/1_18_2.json
mecha/resources/1_19.json
mecha/resources/1_19_1.json
mecha/resources/1_19_2.json
mecha/resources/1_19_3.json
mecha/resources/1_19_4.json
mecha/resources/1_20.json
mecha/resources/1_20_1.json
mecha/resources/1_20_2.json
mecha/resources/1_20_3.json
mecha/resources/1_20_4.json
mecha/resources/1_20_5.json
mecha/resources/1_20_6.json
mecha/resources/1_21.json
mecha/resources/1_21_1.json
mecha/resources/1_21_10.json
mecha/resources/1_21_11.json
mecha/resources/1_21_2.json
mecha/resources/1_21_3.json
mecha/resources/1_21_4.json
mecha/resources/1_21_5.json
mecha-0.102.2.dist-info/licenses/LICENSE
mecha-0.102.2.dist-info/WHEEL
mecha-0.102.2.dist-info/entry_points.txt
mecha-0.102.2.dist-info/METADATA
mecha-0.102.2.dist-info/RECORD
