Metadata-Version: 2.4
Name: mecha
Version: 0.102.2
Summary: A powerful Minecraft command library
Keywords: beet,minecraft,datapack,minecraft-commands,mcfunction
Author: Valentin Berlier
Author-email: Valentin Berlier <berlier.v@gmail.com>
License-Expression: MIT
License-File: LICENSE
Requires-Dist: beet>=0.113.0
Requires-Dist: tokenstream>=1.7.0
Requires-Python: >=3.14
Project-URL: Repository, https://github.com/mcbeet/beet/blob/main/packages/mecha
